jndi_deobfuscate/__init__.py
jndi_deobfuscate/jndi_deobfuscate.py
jndi_deobfuscate-0.0.2.dist-info/LICENSE
jndi_deobfuscate-0.0.2.dist-info/WHEEL
jndi_deobfuscate-0.0.2.dist-info/METADATA
jndi_deobfuscate-0.0.2.dist-info/RECORD
