Metadata-Version: 2.1
Name: jndi-deobfuscate
Version: 0.0.2
Summary: Deobfuscates JNDI strings that are used to exploit systems vulnerable to recent Log4J vulnerabilities
License: Apache-2.0
Author: jinnandjuice
Requires-Python: >=3.9,<4.0
Classifier: License :: OSI Approved :: Apache Software License
Classifier: Programming Language :: Python :: 3
Classifier: Programming Language :: Python :: 3.9
